control_runner/__init__.py
control_runner/cli.py
control_runner/loader.py
control_runner/registry.py
control_runner-0.1.1.dist-info/METADATA
control_runner-0.1.1.dist-info/WHEEL
control_runner-0.1.1.dist-info/entry_points.txt
control_runner-0.1.1.dist-info/top_level.txt
control_runner-0.1.1.dist-info/RECORD
