Metadata-Version: 2.4
Name: control-runner
Version: 0.1.1
Summary: Tool for configuring and running control_arena experiments using .yaml files.
Author-email: Barahlush <baraltiva@gmail.com>
Requires-Python: >=3.13
Requires-Dist: control-arena>=2.1.3
Requires-Dist: click>=8.1.7
Requires-Dist: openai==1.99.2
Requires-Dist: pytest>=8.4.1
Requires-Dist: inspect-ai>=0.3.9
Requires-Dist: pyyaml>=6.0.2
